self_documenting_struct/__init__.py
self_documenting_struct/data_types.py
self_documenting_struct/pack.py
self_documenting_struct/unpack.py
self_documenting_struct-0.9.2.dist-info/COPYING
self_documenting_struct-0.9.2.dist-info/METADATA
self_documenting_struct-0.9.2.dist-info/WHEEL
self_documenting_struct-0.9.2.dist-info/top_level.txt
self_documenting_struct-0.9.2.dist-info/RECORD
