Metadata-Version: 2.1
Name: self_documenting_struct
Version: 0.9.2
Summary: Makes the Python struct library more self-documenting.
Author: npjg
License: GNU GENERAL PUBLIC LICENSE
Project-URL: Homepage, https://github.com/npjg/self_documenting_struct
Project-URL: Repository, https://github.com/npjg/self_documenting_struct
Keywords: struct,reverse-engineering,self-document
Classifier: License :: OSI Approved :: GNU General Public License v3 (GPLv3)
Classifier: Programming Language :: Python :: 3
Classifier: Operating System :: OS Independent
Requires-Python: >=3.9
License-File: COPYING
